{
  "common": {
    "name": "lightify",
    "version": "0.1.5",
    "news": {
      "0.1.5": {
        "en": "added missing file with funtion roundRGB",
        "de": "fehlende datei mit function roundRGB hinzugefügt"
      },
      "0.1.4": {
        "en": "Discovery now via mdns",
        "de": "Discovery jetzt per mdns"
      },
      "0.1.0": {
        "en": "Change to use version 2.x of node-lightify-soef",
        "de": "Umstellung auf Version 2.x von node-lightify-soef"
      },
      "0.0.28": {
        "en": "possible exception in using command state",
        "de": "Mögliche Schutzverletung bei der Verwendung des command Datenpunktes"
      }
    },
    "title": "OSRAM Lightify",
    "desc": {
      "en": "OSRAM Lightify Devices",
      "de": "OSRAM Lightify Devices",
      "ru": "OSRAM Lightify Devices"
    },
    "keywords": [
      "ioBroker",
      "osram",
      "lightify",
      "zigbee",
      "hue"
    ],
    "platform": "Javascript/Node.js",
    "mode": "daemon",
    "icon": "lightify.png",
    "extIcon": "https://raw.githubusercontent.com/soef/iobroker.lightify/master/admin/lightify.png",
    "readme": "https://github.com/soef/iobroker.lightify/blob/master/README.md",
    "loglevel": "info",
    "type": "hardware",
    "enabled": true
  },
  "native": {
    "ip": "",
    "polling": true,
    "intervall": 60
  },
  "instanceObjects": [
  ],
  "objects": [
  ]
}
